amads/__init__.py
amads/all.py
amads/ci.py
amads/utils.py
amads/algorithms/__init__.py
amads/algorithms/entropy.py
amads/algorithms/nnotes.py
amads/algorithms/scale.py
amads/algorithms/slice/__init__.py
amads/algorithms/slice/salami.py
amads/algorithms/slice/slice.py
amads/algorithms/slice/window.py
amads/core/__init__.py
amads/core/basics.py
amads/core/distribution.py
amads/core/time_map.py
amads/core/utils.py
amads/harmony/__init__.py
amads/harmony/consonance/__init__.py
amads/harmony/root_finding/__init__.py
amads/harmony/root_finding/parncutt_1988.py
amads/io/__init__.py
amads/io/pianoroll.py
amads/io/plotdist.py
amads/io/pt_midi_import.py
amads/io/pt_xml_import.py
amads/io/ptscoreread.py
amads/melody/__init__.py
amads/melody/boundary.py
amads/melody/segment_gestalt.py
amads/melody/contour/__init__.py
amads/melody/contour/interpolation_contour.py
amads/melody/contour/step_contour.py
amads/melody/similarity/__init__.py
amads/melody/similarity/melsim.py
amads/music/__init__.py
amads/music/example.py
amads/pitch/__init__.py
amads/pitch/hz2midi.py
amads/pitch/ismonophonic.py
amads/pitch/ivdirdist1.py
amads/pitch/ivdist1.py
amads/pitch/ivdist2.py
amads/pitch/ivsizedist1.py
amads/pitch/pc_set_functions.py
amads/pitch/pc_sets.py
amads/pitch/pcdist1.py
amads/pitch/pcdist2.py
amads/pitch/pitch_mean.py
amads/pitch/serial.py
amads/pitch/transformations.py
amads/pitch/key/profiles.py
amads/polyphony/__init__.py
amads/polyphony/skyline.py
amads/schemata/__init__.py
amads/schemata/partimenti.py
amads/time/__init__.py
amads/time/durdist1.py
amads/time/durdist2.py
amads/time/npvi.py
amads/time/swing.py
amads/time/tempo.py
amads/time/meter/break_it_up.py
amads-0.1.0.dev0.dist-info/LICENSE.md
amads-0.1.0.dev0.dist-info/METADATA
amads-0.1.0.dev0.dist-info/WHEEL
amads-0.1.0.dev0.dist-info/top_level.txt
amads-0.1.0.dev0.dist-info/RECORD
