Metadata-Version: 2.2
Name: amads
Version: 0.1.0.dev0
Summary: A toolkit for symbolic music analysis
Maintainer: Roger Dannenberg, Mark Gotham
Maintainer-email: Peter Harrison <pmch2@cam.ac.uk>
Project-URL: GitHub, https://github.com/music-computing/amads
Project-URL: Documentation website, https://music-computing.github.io/amads/
Classifier: Programming Language :: Python :: 3
Classifier: License :: OSI Approved :: MIT License
Classifier: Operating System :: OS Independent
Requires-Python: >=3.10
License-File: LICENSE.md
Requires-Dist: numpy
Requires-Dist: pandas
Requires-Dist: matplotlib
Requires-Dist: scipy<1.12.0
Requires-Dist: partitura
Requires-Dist: setuptools
Requires-Dist: music21
Requires-Dist: pytest
Requires-Dist: sphinx-gallery
Provides-Extra: dev
Requires-Dist: sphinx; extra == "dev"
Requires-Dist: sphinx-book-theme; extra == "dev"
Requires-Dist: sphinx-autodoc-typehints; extra == "dev"
Requires-Dist: myst-parser; extra == "dev"
Requires-Dist: pre-commit; extra == "dev"
Provides-Extra: test
Requires-Dist: pretty_midi; extra == "test"
Requires-Dist: pytest>=7.0.0; extra == "test"
Requires-Dist: pytest-cov; extra == "test"
Provides-Extra: melsim
Requires-Dist: pandas; extra == "melsim"
Requires-Dist: rpy2; extra == "melsim"
